{
  "score": 63136.765625,
  "genes": [
    {
      "sids": [
        1,
        2,
        0
      ],
      "tarval": 0.4487098157405853,
      "xPatVals": [
        0.5222204327583313,
        -0.7078611254692078,
        0.48821455240249634
      ],
      "tid": 8,
      "yPatVals": [
        0.8528105020523071,
        -0.706351637840271,
        0.8727236390113831
      ]
    },
    {
      "sids": [
        1,
        1,
        1
      ],
      "tarval": 0.5361664295196533,
      "xPatVals": [
        0.10940980911254883,
        -0.6394055485725403,
        -0.31418848037719727
      ],
      "tid": 1,
      "yPatVals": [
        0.9939966797828674,
        0.7688696980476379,
        0.9493606090545654
      ]
    },
    {
      "sids": [
        2,
        2,
        1
      ],
      "tarval": 0,
      "xPatVals": [
        0.9920265674591064,
        -0.992372989654541,
        0.18694773316383362
      ],
      "tid": 4,
      "yPatVals": [
        -0.12602896988391876,
        0.12327130138874054,
        -0.9823698401451111
      ]
    },
    {
      "sids": [
        1,
        0,
        1
      ],
      "tarval": 0.05393294245004654,
      "xPatVals": [
        -0.7389705181121826,
        -0.4641675055027008,
        -0.8364850878715515
      ],
      "tid": 1,
      "yPatVals": [
        -0.6737377047538757,
        -0.8857474327087402,
        -0.5479896664619446
      ]
    },
    {
      "sids": [
        1,
        0,
        1
      ],
      "tarval": 0.9626079201698303,
      "xPatVals": [
        0.9084390997886658,
        0.83395916223526,
        0.9377244114875793
      ],
      "tid": 11,
      "yPatVals": [
        -0.4180172085762024,
        0.5518261790275574,
        -0.3473801910877228
      ]
    },
    {
      "sids": [
        2,
        0,
        1
      ],
      "tarval": 1,
      "xPatVals": [
        0.8910030126571655,
        -0.935219407081604,
        -0.47601497173309326
      ],
      "tid": 8,
      "yPatVals": [
        -0.4539974629878998,
        -0.35406866669654846,
        0.8794372081756592
      ]
    },
    {
      "sids": [
        2,
        2,
        1
      ],
      "tarval": 0,
      "xPatVals": [
        0.9743910431861877,
        0.9351264834403992,
        -0.2553296387195587
      ],
      "tid": 11,
      "yPatVals": [
        0.2248600721359253,
        -0.3543141186237335,
        0.9668540954589844
      ]
    },
    {
      "sids": [
        1,
        1,
        2
      ],
      "tarval": 0,
      "xPatVals": [
        -0.999872624874115,
        -0.5189971923828125,
        0.999977171421051
      ],
      "tid": 3,
      "yPatVals": [
        -0.015958508476614952,
        -0.8547759056091309,
        -0.00675005791708827
      ]
    },
    {
      "sids": [
        2,
        2,
        2
      ],
      "tarval": 1,
      "xPatVals": [
        0.8852037787437439,
        -0.9572575688362122,
        -0.8238441944122314
      ],
      "tid": 13,
      "yPatVals": [
        -0.4652034640312195,
        -0.28923681378364563,
        0.5668162703514099
      ]
    },
    {
      "sids": [
        0,
        2,
        0
      ],
      "tarval": 0,
      "xPatVals": [
        -0.7579964995384216,
        0.05809243395924568,
        -0.6210629343986511
      ],
      "tid": 1,
      "yPatVals": [
        -0.6522586345672607,
        -0.9983112812042236,
        0.783760666847229
      ]
    },
    {
      "sids": [
        2,
        0,
        0
      ],
      "tarval": 0.8982254862785339,
      "xPatVals": [
        -0.9416787624359131,
        -0.5831523537635803,
        0.9770424365997314
      ],
      "tid": 7,
      "yPatVals": [
        0.3365131616592407,
        0.812362790107727,
        0.21304473280906677
      ]
    },
    {
      "sids": [
        2,
        2,
        1
      ],
      "tarval": 0.023747168481349945,
      "xPatVals": [
        -0.9844599962234497,
        0.5067782402038574,
        -0.9783146381378174
      ],
      "tid": 13,
      "yPatVals": [
        -0.17560914158821106,
        0.8620765209197998,
        0.2071245312690735
      ]
    },
    {
      "sids": [
        1,
        0,
        2
      ],
      "tarval": 1,
      "xPatVals": [
        0.9967745542526245,
        -0.5895960330963135,
        0.7702483534812927
      ],
      "tid": 10,
      "yPatVals": [
        -0.08025312423706055,
        -0.8076983094215393,
        0.637744128704071
      ]
    },
    {
      "sids": [
        1,
        2,
        0
      ],
      "tarval": 0,
      "xPatVals": [
        -0.9600730538368225,
        0.01783103123307228,
        -0.9847627282142639
      ],
      "tid": 9,
      "yPatVals": [
        0.2797495722770691,
        -0.999841034412384,
        0.17390339076519012
      ]
    },
    {
      "sids": [
        2,
        2,
        2
      ],
      "tarval": 0.7967759370803833,
      "xPatVals": [
        -0.9862520098686218,
        -0.9993329048156738,
        -0.7192221879959106
      ],
      "tid": 13,
      "yPatVals": [
        0.16524802148342133,
        -0.036520857363939285,
        -0.6947801113128662
      ]
    },
    {
      "sids": [
        1,
        1,
        0
      ],
      "tarval": 1,
      "xPatVals": [
        0.7962549328804016,
        0.805671215057373,
        -0.968157947063446
      ],
      "tid": 11,
      "yPatVals": [
        -0.6049612164497375,
        -0.5923629999160767,
        -0.25034013390541077
      ]
    },
    {
      "sids": [
        2,
        2,
        0
      ],
      "tarval": 0,
      "xPatVals": [
        0.7370026707649231,
        0.9983827471733093,
        0.36534377932548523
      ],
      "tid": 14,
      "yPatVals": [
        0.6758898496627808,
        0.05684851482510567,
        0.9308726787567139
      ]
    },
    {
      "sids": [
        1,
        2,
        0
      ],
      "tarval": 0.6601319313049316,
      "xPatVals": [
        -0.2608528435230255,
        -0.8053815364837646,
        0.052590496838092804
      ],
      "tid": 8,
      "yPatVals": [
        -0.9653785824775696,
        0.5927568078041077,
        0.998616099357605
      ]
    },
    {
      "sids": [
        2,
        2,
        0
      ],
      "tarval": 0,
      "xPatVals": [
        0.4697781205177307,
        -0.3963090479373932,
        -0.867594838142395
      ],
      "tid": 10,
      "yPatVals": [
        0.8827844858169556,
        0.9181172251701355,
        -0.49727189540863037
      ]
    },
    {
      "sids": [
        1,
        0,
        1
      ],
      "tarval": 0.04307145997881889,
      "xPatVals": [
        -0.9842360615730286,
        0.536728024482727,
        -0.5512922406196594
      ],
      "tid": 6,
      "yPatVals": [
        0.17685960233211517,
        0.8437552452087402,
        0.8343121409416199
      ]
    }
  ]
}