{
  "score": 83990.1484375,
  "genes": [
    {
      "sids": [
        1,
        2,
        0
      ],
      "tarval": 0.2383670210838318,
      "xPatVals": [
        0.7874755263328552,
        -0.9988980889320374,
        0.953352689743042
      ],
      "tid": 8,
      "yPatVals": [
        0.6163459420204163,
        0.04693232476711273,
        0.301858514547348
      ]
    },
    {
      "sids": [
        1,
        1,
        1
      ],
      "tarval": 0.47681522369384766,
      "xPatVals": [
        0.1887456476688385,
        -0.14455324411392212,
        0.1262180060148239
      ],
      "tid": 1,
      "yPatVals": [
        0.9820259809494019,
        0.9894970655441284,
        0.9920024871826172
      ]
    },
    {
      "sids": [
        2,
        2,
        1
      ],
      "tarval": 0,
      "xPatVals": [
        0.952573835849762,
        -0.8234925270080566,
        0.08436784148216248
      ],
      "tid": 4,
      "yPatVals": [
        0.3043075501918793,
        -0.567327082157135,
        -0.9964346885681152
      ]
    },
    {
      "sids": [
        1,
        0,
        1
      ],
      "tarval": 0,
      "xPatVals": [
        -0.999379575252533,
        -0.6550343036651611,
        -0.6795652508735657
      ],
      "tid": 1,
      "yPatVals": [
        -0.03522138297557831,
        -0.7555991411209106,
        0.7336150407791138
      ]
    },
    {
      "sids": [
        1,
        2,
        1
      ],
      "tarval": 1,
      "xPatVals": [
        0.8906395435333252,
        0.6371479034423828,
        0.4322218894958496
      ],
      "tid": 11,
      "yPatVals": [
        -0.4547100365161896,
        0.7707416415214539,
        -0.9017673134803772
      ]
    },
    {
      "sids": [
        2,
        0,
        1
      ],
      "tarval": 0.7719436287879944,
      "xPatVals": [
        0.8120689392089844,
        -0.8133648037910461,
        -0.674816370010376
      ],
      "tid": 8,
      "yPatVals": [
        -0.5835615992546082,
        -0.5817540287971497,
        0.7379856705665588
      ]
    },
    {
      "sids": [
        0,
        2,
        1
      ],
      "tarval": 0,
      "xPatVals": [
        0.9654059410095215,
        0.8760344982147217,
        -0.9165743589401245
      ],
      "tid": 11,
      "yPatVals": [
        0.2607514560222626,
        -0.48224833607673645,
        0.39986419677734375
      ]
    },
    {
      "sids": [
        1,
        1,
        2
      ],
      "tarval": 0,
      "xPatVals": [
        -0.5294731259346008,
        -0.8335340619087219,
        0.9976823925971985
      ],
      "tid": 3,
      "yPatVals": [
        -0.8483267426490784,
        -0.5524681210517883,
        -0.06804279237985611
      ]
    },
    {
      "sids": [
        2,
        2,
        2
      ],
      "tarval": 0.44823944568634033,
      "xPatVals": [
        0.4401355981826782,
        -0.6048023104667664,
        -0.5089647173881531
      ],
      "tid": 13,
      "yPatVals": [
        -0.8979313373565674,
        -0.7963756918907166,
        -0.8607873916625977
      ]
    },
    {
      "sids": [
        0,
        2,
        0
      ],
      "tarval": 0.02748420089483261,
      "xPatVals": [
        -0.409028559923172,
        0.7221470475196838,
        -0.5512078404426575
      ],
      "tid": 1,
      "yPatVals": [
        -0.9125216007232666,
        -0.6917396187782288,
        0.8343679904937744
      ]
    },
    {
      "sids": [
        2,
        0,
        0
      ],
      "tarval": 0,
      "xPatVals": [
        -0.9408513903617859,
        -0.7917661070823669,
        0.9893223643302917
      ],
      "tid": 7,
      "yPatVals": [
        0.3388194441795349,
        -0.610824465751648,
        -0.14574310183525085
      ]
    },
    {
      "sids": [
        2,
        2,
        1
      ],
      "tarval": 0,
      "xPatVals": [
        -0.3801717460155487,
        0.9978927969932556,
        -0.879732608795166
      ],
      "tid": 13,
      "yPatVals": [
        -0.9249159097671509,
        0.06488305330276489,
        -0.47546878457069397
      ]
    },
    {
      "sids": [
        1,
        0,
        2
      ],
      "tarval": 0.5532046556472778,
      "xPatVals": [
        0.9562391638755798,
        0.29409950971603394,
        0.9795753359794617
      ],
      "tid": 10,
      "yPatVals": [
        -0.2925862669944763,
        -0.9557747840881348,
        0.20107759535312653
      ]
    },
    {
      "sids": [
        1,
        2,
        0
      ],
      "tarval": 0,
      "xPatVals": [
        -0.7124515771865845,
        0.46060648560523987,
        -0.776187539100647
      ],
      "tid": 1,
      "yPatVals": [
        -0.7017212510108948,
        -0.8876044154167175,
        0.6305022239685059
      ]
    },
    {
      "sids": [
        2,
        2,
        2
      ],
      "tarval": 0.6152787804603577,
      "xPatVals": [
        -0.8911132216453552,
        -0.9859901666641235,
        -0.9625808596611023
      ],
      "tid": 13,
      "yPatVals": [
        0.4537809193134308,
        -0.16680331528186798,
        -0.2709948718547821
      ]
    },
    {
      "sids": [
        1,
        1,
        0
      ],
      "tarval": 0.9085605144500732,
      "xPatVals": [
        0.8141695261001587,
        0.8489302396774292,
        -0.725724995136261
      ],
      "tid": 11,
      "yPatVals": [
        -0.5806272625923157,
        0.5285049080848694,
        -0.6879848837852478
      ]
    },
    {
      "sids": [
        1,
        2,
        0
      ],
      "tarval": 0.07141487300395966,
      "xPatVals": [
        -0.369453489780426,
        0.9550638794898987,
        0.3052171766757965
      ],
      "tid": 14,
      "yPatVals": [
        0.9292492866516113,
        0.29640015959739685,
        0.9522827863693237
      ]
    },
    {
      "sids": [
        1,
        2,
        0
      ],
      "tarval": 0.3106500804424286,
      "xPatVals": [
        -0.17934727668762207,
        0.6153560876846313,
        -0.6762255430221558
      ],
      "tid": 8,
      "yPatVals": [
        -0.9837857484817505,
        0.7882493138313293,
        0.7366946935653687
      ]
    },
    {
      "sids": [
        2,
        2,
        0
      ],
      "tarval": 0.5806978940963745,
      "xPatVals": [
        0.10282272845506668,
        -0.7371618747711182,
        -0.9944738745689392
      ],
      "tid": 10,
      "yPatVals": [
        0.9946997165679932,
        0.6757161617279053,
        -0.10498397797346115
      ]
    },
    {
      "sids": [
        1,
        0,
        1
      ],
      "tarval": 0,
      "xPatVals": [
        -0.296459823846817,
        0.9343817234039307,
        -0.7456791400909424
      ],
      "tid": 6,
      "yPatVals": [
        -0.9550452828407288,
        0.356273353099823,
        0.6663052439689636
      ]
    }
  ]
}