{
  "score": 68935.703125,
  "genes": [
    {
      "sids": [
        0,
        0,
        1
      ],
      "tarval": 0,
      "xPatVals": [
        0.3397448658943176,
        0.0990133285522461,
        -0.3282555341720581
      ],
      "tid": 1,
      "yPatVals": [
        0.9405176639556885,
        -0.9950860738754272,
        0.9445890188217163
      ]
    },
    {
      "sids": [
        2,
        1,
        0
      ],
      "tarval": 0,
      "xPatVals": [
        -0.9483184814453125,
        -0.1517808586359024,
        0.9992333650588989
      ],
      "tid": 10,
      "yPatVals": [
        0.3173201084136963,
        -0.9884142279624939,
        0.03914825990796089
      ]
    },
    {
      "sids": [
        1,
        0,
        2
      ],
      "tarval": 0.6473623514175415,
      "xPatVals": [
        0.9430455565452576,
        -0.4578966498374939,
        -0.9360049366950989
      ],
      "tid": 9,
      "yPatVals": [
        0.3326636254787445,
        0.8890053629875183,
        -0.35198691487312317
      ]
    },
    {
      "sids": [
        1,
        0,
        1
      ],
      "tarval": 0.6680994629859924,
      "xPatVals": [
        0.3643089532852173,
        -0.9971577525138855,
        0.6578659415245056
      ],
      "tid": 13,
      "yPatVals": [
        -0.9312781691551208,
        0.07534155994653702,
        0.753135085105896
      ]
    },
    {
      "sids": [
        0,
        0,
        1
      ],
      "tarval": 0.06504595279693604,
      "xPatVals": [
        0.09597340226173401,
        0.9700254797935486,
        -0.2869795858860016
      ],
      "tid": 6,
      "yPatVals": [
        -0.9953839182853699,
        0.24300311505794525,
        -0.9579366445541382
      ]
    },
    {
      "sids": [
        2,
        2,
        2
      ],
      "tarval": 0,
      "xPatVals": [
        -0.14324718713760376,
        -0.16602855920791626,
        0.498954176902771
      ],
      "tid": 1,
      "yPatVals": [
        -0.989686906337738,
        0.9861209988594055,
        0.8666284084320068
      ]
    },
    {
      "sids": [
        2,
        0,
        2
      ],
      "tarval": 0,
      "xPatVals": [
        0.6989977955818176,
        0.9962722063064575,
        0.9277408123016357
      ],
      "tid": 2,
      "yPatVals": [
        0.7151237726211548,
        -0.0862649530172348,
        -0.37322524189949036
      ]
    },
    {
      "sids": [
        1,
        0,
        0
      ],
      "tarval": 1,
      "xPatVals": [
        0.2992117702960968,
        -0.6367814540863037,
        -0.6623194813728333
      ],
      "tid": 10,
      "yPatVals": [
        0.9541866779327393,
        0.7710443735122681,
        0.7492215037345886
      ]
    },
    {
      "sids": [
        2,
        2,
        2
      ],
      "tarval": 0.06962965428829193,
      "xPatVals": [
        -0.25880250334739685,
        0.9993406534194946,
        0.11433343589305878
      ],
      "tid": 9,
      "yPatVals": [
        -0.9659302830696106,
        0.03630688041448593,
        0.9934424757957458
      ]
    },
    {
      "sids": [
        2,
        2,
        2
      ],
      "tarval": 1,
      "xPatVals": [
        -0.8279984593391418,
        0.21472620964050293,
        -0.9309713244438171
      ],
      "tid": 12,
      "yPatVals": [
        -0.5607303977012634,
        0.9766742587089539,
        0.36509236693382263
      ]
    },
    {
      "sids": [
        0,
        2,
        1
      ],
      "tarval": 0.26202213764190674,
      "xPatVals": [
        0.922073483467102,
        -0.807623028755188,
        -0.9659197330474854
      ],
      "tid": 2,
      "yPatVals": [
        0.3870149850845337,
        0.5896990299224854,
        0.25884169340133667
      ]
    },
    {
      "sids": [
        0,
        1,
        2
      ],
      "tarval": 1,
      "xPatVals": [
        -0.818754255771637,
        0.29205313324928284,
        -0.9786327481269836
      ],
      "tid": 6,
      "yPatVals": [
        0.574144184589386,
        0.956402063369751,
        -0.20561593770980835
      ]
    },
    {
      "sids": [
        0,
        0,
        0
      ],
      "tarval": 0.5584782361984253,
      "xPatVals": [
        -0.5017518401145935,
        -0.4636407494544983,
        -0.9836465120315552
      ],
      "tid": 2,
      "yPatVals": [
        0.8650115728378296,
        0.886023223400116,
        0.1801099181175232
      ]
    },
    {
      "sids": [
        2,
        0,
        0
      ],
      "tarval": 0,
      "xPatVals": [
        -0.7204107046127319,
        0.8082491755485535,
        0.9418271780014038
      ],
      "tid": 13,
      "yPatVals": [
        0.6935477256774902,
        0.5888405442237854,
        -0.3360976278781891
      ]
    },
    {
      "sids": [
        0,
        0,
        2
      ],
      "tarval": 0.6599493026733398,
      "xPatVals": [
        -0.49368205666542053,
        0.9935158491134644,
        -0.16645658016204834
      ],
      "tid": 10,
      "yPatVals": [
        0.8696424961090088,
        0.11369384825229645,
        0.9860487580299377
      ]
    },
    {
      "sids": [
        1,
        1,
        0
      ],
      "tarval": 0.7932334542274475,
      "xPatVals": [
        0.15061752498149872,
        -0.6266657114028931,
        -0.3518756926059723
      ],
      "tid": 1,
      "yPatVals": [
        -0.9885920882225037,
        -0.7792881727218628,
        -0.9360467195510864
      ]
    },
    {
      "sids": [
        1,
        0,
        0
      ],
      "tarval": 0.2932552099227905,
      "xPatVals": [
        -0.9959726333618164,
        -0.9997376203536987,
        0.07397649437189102
      ],
      "tid": 12,
      "yPatVals": [
        -0.08965791761875153,
        -0.02290429174900055,
        0.9972599744796753
      ]
    },
    {
      "sids": [
        1,
        2,
        0
      ],
      "tarval": 0.6178333759307861,
      "xPatVals": [
        -0.08209960162639618,
        0.7238239645957947,
        -0.9260504245758057
      ],
      "tid": 5,
      "yPatVals": [
        -0.9966241121292114,
        -0.6899845600128174,
        0.3773998022079468
      ]
    },
    {
      "sids": [
        1,
        0,
        0
      ],
      "tarval": 0.12620556354522705,
      "xPatVals": [
        -0.9117156863212585,
        -0.9321422576904297,
        -0.9972444176673889
      ],
      "tid": 2,
      "yPatVals": [
        0.41082167625427246,
        0.36209243535995483,
        -0.07418634742498398
      ]
    },
    {
      "sids": [
        2,
        1,
        0
      ],
      "tarval": 0,
      "xPatVals": [
        -0.8071057796478271,
        -0.19168643653392792,
        0.8166069388389587
      ],
      "tid": 0,
      "yPatVals": [
        -0.5904070138931274,
        -0.9814562201499939,
        0.5771941542625427
      ]
    }
  ]
}